mocker_db/__init__.py
mocker_db/cli.py
mocker_db/mocker_db.py
mocker_db/routes.py
mocker_db/setup.py
mocker_db/.paa.tracking/.drawio
mocker_db/.paa.tracking/.paa.config
mocker_db/.paa.tracking/.paa.version
mocker_db/.paa.tracking/lsts_package_versions.yml
mocker_db/.paa.tracking/notebook.ipynb
mocker_db/.paa.tracking/package_licenses.json
mocker_db/.paa.tracking/package_mapping.json
mocker_db/.paa.tracking/release_notes.md
mocker_db/.paa.tracking/version_logs.csv
mocker_db/.paa.tracking/extra_docs/cli.md
mocker_db/.paa.tracking/python_modules/mocker_db.py
mocker_db/.paa.tracking/python_modules/components/mocker_db_deps/data_types.py
mocker_db/.paa.tracking/python_modules/components/mocker_db_deps/llm_filter_connector.py
mocker_db/.paa.tracking/python_modules/components/mocker_db_deps/llm_handler.py
mocker_db/.paa.tracking/python_modules/components/mocker_db_deps/memory_management.py
mocker_db/.paa.tracking/python_modules/components/mocker_db_deps/mocker_connector.py
mocker_db/.paa.tracking/python_modules/components/mocker_db_deps/mocker_similarity_search.py
mocker_db/.paa.tracking/python_modules/components/mocker_db_deps/other.py
mocker_db/.paa.tracking/python_modules/components/mocker_db_deps/response_descriptions.py
mocker_db/.paa.tracking/python_modules/components/mocker_db_deps/sentence_transformer_embedder.py
mocker_db/mkdocs/mkdocs.yml
mocker_db/mkdocs/docs/cli.md
mocker_db/mkdocs/docs/description.md
mocker_db/mkdocs/docs/flow.md
mocker_db/mkdocs/docs/flow.png
mocker_db/mkdocs/docs/index.md
mocker_db/mkdocs/docs/release-notes.md
mocker_db/mkdocs/docs/css/extra.css
mocker_db/mkdocs/site/404.html
mocker_db/mkdocs/site/flow.png
mocker_db/mkdocs/site/index.html
mocker_db/mkdocs/site/sitemap.xml
mocker_db/mkdocs/site/sitemap.xml.gz
mocker_db/mkdocs/site/assets/images/favicon.png
mocker_db/mkdocs/site/assets/javascripts/bundle.fe8b6f2b.min.js
mocker_db/mkdocs/site/assets/javascripts/bundle.fe8b6f2b.min.js.map
mocker_db/mkdocs/site/assets/javascripts/lunr/tinyseg.js
mocker_db-0.3.0.dist-info/LICENSE
mocker_db-0.3.0.dist-info/METADATA
mocker_db-0.3.0.dist-info/WHEEL
mocker_db-0.3.0.dist-info/entry_points.txt
mocker_db-0.3.0.dist-info/top_level.txt
mocker_db-0.3.0.dist-info/RECORD
