Metadata-Version: 2.1
Name: mocker_db
Version: 0.3.0
Summary: A mock handler for simulating a vector database.
Home-page: https://kiril-mordan.github.io/reusables/mocker_db/
Author: Kyrylo Mordan
Author-email: parachute.repo@gmail.com
License: mit
Keywords: aa-paa-tool
Classifier: Development Status :: 3 - Alpha
Classifier: Intended Audience :: Developers
Classifier: Intended Audience :: Science/Research
Classifier: Programming Language :: Python :: 3
Classifier: Programming Language :: Python :: 3.9
Classifier: Programming Language :: Python :: 3.10
Classifier: Programming Language :: Python :: 3.11
Classifier: Programming Language :: Python :: 3.12
Classifier: License :: OSI Approved :: MIT License
Classifier: Topic :: Scientific/Engineering
License-File: LICENSE
Requires-Dist: attrs>=23.1.0
Requires-Dist: httpx
Requires-Dist: numpy==1.26.0
Requires-Dist: pyyaml
Requires-Dist: aiohttp
Requires-Dist: psutil
Requires-Dist: gridlooper>=0.0.1
Requires-Dist: attrsx
Requires-Dist: nest-asyncio
Requires-Dist: requests
Requires-Dist: dill>=0.3.7
Requires-Dist: pydantic
Requires-Dist: pympler==1.0.1
Requires-Dist: fastapi
Requires-Dist: click==8.1.7
Provides-Extra: all
Requires-Dist: torch; extra == "all"
Requires-Dist: hnswlib==0.8.0; extra == "all"
Requires-Dist: openai; extra == "all"
Requires-Dist: sentence-transformers; extra == "all"
Requires-Dist: ollama; extra == "all"
Provides-Extra: hnswlib
Requires-Dist: hnswlib==0.8.0; extra == "hnswlib"
Provides-Extra: ollama
Requires-Dist: ollama; extra == "ollama"
Provides-Extra: openai
Requires-Dist: openai; extra == "openai"
Provides-Extra: sentence-transformers
Requires-Dist: sentence-transformers; extra == "sentence-transformers"
Provides-Extra: torch
Requires-Dist: torch; extra == "torch"
